{
    "$schema": "./config_schema.json",
    "components":[
        {
            "name":"FrontESTOP",
            "type":"SdcNode",
            "mode":"Emulate",
            "emulation_source":{"device":"Virtual1","type":"SW","port":"P5"},
            "harness_connection":{"Connector":"DASH_J2", "Pin":3}
        },
        {
            "name":"BOTS",
            "type":"SdcNode",
            "mode":"Emulate",
            "emulation_source":{"device":"Virtual1","type":"SW","port":"P6"},
            "harness_connection":{"Connector":"DASH_J2", "Pin":3}
        }
    ],
    "emulators":[
        {
            "name":"Virtual1",
            "type":"virtual"
        }
    ]
}
